common_stats/__init__.py
common_stats/statistics.py
common_stats_thaichim-0.0.9.dist-info/licenses/LICENSE
tests/__init__.py
tests/test_statistics.py
common_stats_thaichim-0.0.9.dist-info/METADATA
common_stats_thaichim-0.0.9.dist-info/WHEEL
common_stats_thaichim-0.0.9.dist-info/top_level.txt
common_stats_thaichim-0.0.9.dist-info/RECORD
