Metadata-Version: 2.4
Name: common_stats-thaichim
Version: 0.0.9
Summary: A simple library for basic statistical calculations
Author: Nawawan Thaichim
Author-email: woonzy09@email.com
License: MIT
Requires-Python: >=3.7
License-File: LICENSE
Requires-Dist: pytest
Dynamic: author
Dynamic: author-email
Dynamic: description
Dynamic: description-content-type
Dynamic: license
Dynamic: license-file
Dynamic: requires-dist
Dynamic: requires-python
Dynamic: summary
